frame_logging/__init__.py
frame_logging/apps.py
frame_logging/formatter.py
frame_logging/log.py
frame_logging/log_settings.py
frame_logging-0.2.1.dist-info/DESCRIPTION.rst
frame_logging-0.2.1.dist-info/METADATA
frame_logging-0.2.1.dist-info/RECORD
frame_logging-0.2.1.dist-info/WHEEL
frame_logging-0.2.1.dist-info/metadata.json
frame_logging-0.2.1.dist-info/top_level.txt
