Metadata-Version: 2.0
Name: frame-logging
Version: 0.2.1
Summary: Your project description goes here
Home-page: https://github.com/ItsfBisounours/frame_logging
Author: Romain DA COSTA VIEIRA
Author-email: romain.da-costa-vieira@itsfactory.fr
License: MIT
Keywords: frame_logging
Platform: UNKNOWN
Classifier: Development Status :: 3 - Alpha
Classifier: Framework :: Django
Classifier: Framework :: Django :: 1.10
Classifier: Intended Audience :: Developers
Classifier: License :: OSI Approved :: BSD License
Classifier: Natural Language :: English
Classifier: Programming Language :: Python :: 2
Classifier: Programming Language :: Python :: 2.7
Classifier: Programming Language :: Python :: 3
Classifier: Programming Language :: Python :: 3.4
Classifier: Programming Language :: Python :: 3.5
